<dc:title>Buscador UOL</dc:title>
<dc:creator>UOL</dc:creator>
<dc:subject>Buscador/portal</dc:subject>
<dc:description>Página principal do buscador do site UOL separado por temas.</dc:description>
<dc:publisher>UOL</dc:publisher>
<dc:date>2000-08-16</dc:date>
<dc:type>Texto/Imagem</dc:type>
<dc:format>Página Web</dc:format>
<dc:identifier>http://www.uol.com.br/busca/</dc:identifier>
<dc:source>http://www.uol.com.br</dc:source>
<dc:language>PT-BR</dc:language>
<dc:relation>https://web.archive.org/web/20000816093351/http://www.uol.com.br/busca/</dc:relation>
<dc:coverage>UOL</dc:coverage>
<dc:coverage>2000</dc:coverage>
<dc:rights>Todos os direitos reservados</dc:rights>